<annotation verified="no">
  <folder>20211231</folder>
  <filename>02389</filename>
  <path>D:\nainiushujuji\20211231\02389.jpg</path>
  <source>
    <database>Unknown</database>
  </source>
  <size>
    <width>1920</width>
    <height>1080</height>
    <depth>3</depth>
  </size>
  <segmented>0</segmented>
  <object>
    <name>cow</name>
    <pose>Unspecified</pose>
    <truncated>0</truncated>
    <Difficult>0</Difficult>
    <bndbox>
      <xmin>710</xmin>
      <ymin>292</ymin>
      <xmax>1062</xmax>
      <ymax>828</ymax>
    </bndbox>
  </object>
  <object>
    <name>cow</name>
    <pose>Unspecified</pose>
    <truncated>0</truncated>
    <Difficult>0</Difficult>
    <bndbox>
      <xmin>1472</xmin>
      <ymin>330</ymin>
      <xmax>1823</xmax>
      <ymax>805</ymax>
    </bndbox>
  </object>
  <object>
    <name>cow</name>
    <pose>Unspecified</pose>
    <truncated>0</truncated>
    <Difficult>0</Difficult>
    <bndbox>
      <xmin>1304</xmin>
      <ymin>324</ymin>
      <xmax>1600</xmax>
      <ymax>886</ymax>
    </bndbox>
  </object>
  <object>
    <name>cow</name>
    <pose>Unspecified</pose>
    <truncated>0</truncated>
    <Difficult>0</Difficult>
    <bndbox>
      <xmin>345</xmin>
      <ymin>265</ymin>
      <xmax>683</xmax>
      <ymax>757</ymax>
    </bndbox>
  </object>
</annotation>