<annotation verified="no">
  <folder>20220101</folder>
  <filename>05108</filename>
  <path>D:\nainiushujuji\20220101\05108.jpg</path>
  <source>
    <database>Unknown</database>
  </source>
  <size>
    <width>1920</width>
    <height>1080</height>
    <depth>3</depth>
  </size>
  <segmented>0</segmented>
  <object>
    <name>cow</name>
    <pose>Unspecified</pose>
    <truncated>0</truncated>
    <Difficult>0</Difficult>
    <bndbox>
      <xmin>122</xmin>
      <ymin>309</ymin>
      <xmax>677</xmax>
      <ymax>738</ymax>
    </bndbox>
  </object>
  <object>
    <name>cow</name>
    <pose>Unspecified</pose>
    <truncated>0</truncated>
    <Difficult>0</Difficult>
    <bndbox>
      <xmin>1473</xmin>
      <ymin>332</ymin>
      <xmax>1681</xmax>
      <ymax>851</ymax>
    </bndbox>
  </object>
  <object>
    <name>cow</name>
    <pose>Unspecified</pose>
    <truncated>0</truncated>
    <Difficult>0</Difficult>
    <bndbox>
      <xmin>1308</xmin>
      <ymin>330</ymin>
      <xmax>1550</xmax>
      <ymax>774</ymax>
    </bndbox>
  </object>
  <object>
    <name>cow</name>
    <pose>Unspecified</pose>
    <truncated>0</truncated>
    <Difficult>0</Difficult>
    <bndbox>
      <xmin>1643</xmin>
      <ymin>361</ymin>
      <xmax>1885</xmax>
      <ymax>657</ymax>
    </bndbox>
  </object>
</annotation>