<annotation verified="no">
  <folder>20220102</folder>
  <filename>08030</filename>
  <path>D:\nainiushujuji\20220102\08030.jpg</path>
  <source>
    <database>Unknown</database>
  </source>
  <size>
    <width>1920</width>
    <height>1080</height>
    <depth>3</depth>
  </size>
  <segmented>0</segmented>
  <object>
    <name>cow</name>
    <pose>Unspecified</pose>
    <truncated>0</truncated>
    <Difficult>0</Difficult>
    <bndbox>
      <xmin>1331</xmin>
      <ymin>634</ymin>
      <xmax>1837</xmax>
      <ymax>770</ymax>
    </bndbox>
  </object>
  <object>
    <name>cow</name>
    <pose>Unspecified</pose>
    <truncated>0</truncated>
    <Difficult>0</Difficult>
    <bndbox>
      <xmin>1118</xmin>
      <ymin>178</ymin>
      <xmax>1341</xmax>
      <ymax>303</ymax>
    </bndbox>
  </object>
  <object>
    <name>cow</name>
    <pose>Unspecified</pose>
    <truncated>0</truncated>
    <Difficult>0</Difficult>
    <bndbox>
      <xmin>589</xmin>
      <ymin>242</ymin>
      <xmax>773</xmax>
      <ymax>372</ymax>
    </bndbox>
  </object>
  <object>
    <name>cow</name>
    <pose>Unspecified</pose>
    <truncated>0</truncated>
    <Difficult>0</Difficult>
    <bndbox>
      <xmin>1058</xmin>
      <ymin>240</ymin>
      <xmax>1229</xmax>
      <ymax>344</ymax>
    </bndbox>
  </object>
</annotation>